svahnar/__init__.py
svahnar/_base_client.py
svahnar/_client.py
svahnar/_compat.py
svahnar/_constants.py
svahnar/_exceptions.py
svahnar/_files.py
svahnar/_models.py
svahnar/_qs.py
svahnar/_resource.py
svahnar/_response.py
svahnar/_streaming.py
svahnar/_types.py
svahnar/_version.py
svahnar/py.typed
svahnar/_utils/__init__.py
svahnar/_utils/_compat.py
svahnar/_utils/_datetime_parse.py
svahnar/_utils/_logs.py
svahnar/_utils/_proxy.py
svahnar/_utils/_reflection.py
svahnar/_utils/_resources_proxy.py
svahnar/_utils/_streams.py
svahnar/_utils/_sync.py
svahnar/_utils/_transform.py
svahnar/_utils/_typing.py
svahnar/_utils/_utils.py
svahnar/lib/.keep
svahnar/resources/__init__.py
svahnar/resources/agents.py
svahnar/resources/auth.py
svahnar/types/__init__.py
svahnar/types/agent_bulk_delete_params.py
svahnar/types/agent_create_params.py
svahnar/types/agent_delete_params.py
svahnar/types/agent_download_params.py
svahnar/types/agent_generate_chat_history_params.py
svahnar/types/agent_list_params.py
svahnar/types/agent_reconfigure_params.py
svahnar/types/agent_retrieve_params.py
svahnar/types/agent_run_params.py
svahnar/types/agent_test_params.py
svahnar/types/agent_update_info_params.py
svahnar/types/agent_validate_params.py
svahnar/types/agent_validate_response.py
svahnar/types/auth_login_params.py
svahnar-1.7.1.dist-info/METADATA
svahnar-1.7.1.dist-info/WHEEL
svahnar-1.7.1.dist-info/licenses/LICENSE
svahnar-1.7.1.dist-info/RECORD
